[
  {
    "nombre": "Juan",
    "apellido": "Perez",
    "dni": "20111222",
    "email": "juan.perez@talentoevolutivo.com",
    "participacion": 40,
    "permisos": [
      "EMPRESAS",
      "EMPLEADOS",
      "LIQUIDACIONES",
      "SOCIOS",
      "AUDITORIA", 
      "NOVEDADES"
    ],
    "activo": true,
    "password": 1234,
    "rol": "socio"
  },
  {
    "nombre": "Luis",
    "apellido": "Montán",
    "dni": "25333444",
    "email": "luis.montan@talentoevolutivo.com",
    "participacion": 35,
    "permisos": ["EMPRESAS", "NOVEDADES", "LIQUIDACIONES"],
    "activo": true,
    "password": 12345,
    "rol": "socio"
  },
  {
    "nombre": "Rio",
    "apellido": "Mario",
    "dni": "30555666",
    "email": "mario.rio@talentoevolutivo.com",
    "participacion": 25,
    "permisos": ["EMPRESAS", "AUDITORIA"],
    "activo": true,
    "password": 123456,
    "rol": "socio"
  }
]
